akrule/__init__.py
akrule/nlp/__init__.py
akrule/nlp/_akcossimnlp.py
akrule/time_series/__init__.py
akrule/time_series/_akrulebasedts.py
akrule/time_series/_datasets.py
akrule/time_series/utils.py
test/__init__.py
test/nlp/__init__.py
test/nlp/test_akcossimnlp.py
test/time_series/__init__.py
test/time_series/test_akrulebasedts.py
akrule-0.1.4.dist-info/LICENSE
akrule-0.1.4.dist-info/METADATA
akrule-0.1.4.dist-info/WHEEL
akrule-0.1.4.dist-info/top_level.txt
akrule-0.1.4.dist-info/RECORD
